[{"sku":707308,"name":"Texas Sensitive Pea","brand":"Sitework & Site Utilities","generic name":"Transcof"},
{"sku":729432,"name":"Torrey's Milkvetch","brand":"Waterproofing & Caulking","generic name":"Cookley"},
{"sku":682890,"name":"Chinquapin","brand":"Ornamental Railings","generic name":"Ronstring"},
{"sku":627310,"name":"Variableleaf False Ohelo","brand":"Rebar & Wire Mesh Install","generic name":"Sonsing"},
{"sku":136427,"name":"Awl-leaf Lilaea","brand":"Temp Fencing, Decorative Fencing and Gates","generic name":"Subin"},
{"sku":61404,"name":"Dogtooth Violet","brand":"EIFS","generic name":"Solarbreeze"},
{"sku":3455,"name":"Labrador Bryum Moss","brand":"Framing (Wood)","generic name":"Vagram"},
{"sku":41299,"name":"Horseweed","brand":"Structural and Misc Steel (Fabrication)","generic name":"Cardguard"},
{"sku":916299,"name":"Green Bulrush","brand":"Structural and Misc Steel (Fabrication)","generic name":"Duobam"},
{"sku":794287,"name":"Rusty Lupine","brand":"Prefabricated Aluminum Metal Canopies","generic name":"Latlux"},
{"sku":466785,"name":"Variegated Orchid","brand":"Roofing (Metal)","generic name":"Sonair"},
{"sku":321290,"name":"Chick Pea","brand":"Termite Control","generic name":"Toughjoyfax"},
{"sku":64569,"name":"Debeque Phacelia","brand":"Fire Sprinkler System","generic name":"Subin"},
{"sku":544409,"name":"Sierra Bluecup","brand":"Marlite Panels (FED)","generic name":"Lotstring"},
{"sku":867915,"name":"Starlet Spineflower","brand":"RF Shielding","generic name":"Bigtax"},
{"sku":699124,"name":"False Golden Polypody","brand":"Overhead Doors","generic name":"Voyatouch"},
{"sku":869534,"name":"Heartleaf Bittercress","brand":"Waterproofing & Caulking","generic name":"Subin"},
{"sku":348316,"name":"Pyxine Lichen","brand":"Structural & Misc Steel Erection","generic name":"Voyatouch"},
{"sku":925629,"name":"Agoseris","brand":"Electrical and Fire Alarm","generic name":"Redhold"},
{"sku":978008,"name":"Proctor's Vriesea","brand":"Marlite Panels (FED)","generic name":"Bitchip"},
{"sku":462098,"name":"Desert Agave","brand":"Framing (Wood)","generic name":"Bigtax"},
{"sku":919425,"name":"Oatgrass","brand":"Fire Protection","generic name":"Solarbreeze"},
{"sku":788934,"name":"Victor's Gooseberry","brand":"Fire Sprinkler System","generic name":"Kanlam"},
{"sku":292121,"name":"Oneflower Fleabane","brand":"Plumbing & Medical Gas","generic name":"Y-Solowarm"},
{"sku":753927,"name":"Camphor","brand":"Fire Protection","generic name":"Overhold"},
{"sku":351412,"name":"Firethorn","brand":"Roofing (Asphalt)","generic name":"Zathin"},
{"sku":414291,"name":"Bush Monkeyflower","brand":"Roofing (Metal)","generic name":"Bigtax"},
{"sku":610873,"name":"Brown Bentgrass","brand":"RF Shielding","generic name":"Asoka"},
{"sku":300055,"name":"Pink Alumroot","brand":"Glass & Glazing","generic name":"Asoka"},
{"sku":995628,"name":"Loomis' Thimblehead","brand":"Electrical","generic name":"Bytecard"},
{"sku":290033,"name":"American Grama","brand":"Hard Tile & Stone","generic name":"Span"},
{"sku":354543,"name":"Rushpea","brand":"Construction Clean and Final Clean","generic name":"Lotstring"},
{"sku":988750,"name":"Porocyphus Lichen","brand":"Drilled Shafts","generic name":"Biodex"},
{"sku":52028,"name":"Buckley's Beardtongue","brand":"Granite Surfaces","generic name":"Tempsoft"},
{"sku":156502,"name":"Faurie's Panicgrass","brand":"Fire Protection","generic name":"Sonair"},
{"sku":509361,"name":"Molokai Twinsorus Fern","brand":"Framing (Steel)","generic name":"Span"},
{"sku":67046,"name":"Stipulate Leaf-flower","brand":"Granite Surfaces","generic name":"Overhold"},
{"sku":298928,"name":"Thinleaf Sedge","brand":"Site Furnishings","generic name":"Rank"},
{"sku":209067,"name":"Bulbophyllum","brand":"Structural & Misc Steel Erection","generic name":"Cardify"},
{"sku":926701,"name":"Snowbed Draba","brand":"Site Furnishings","generic name":"Vagram"},
{"sku":619998,"name":"Hoary Ragwort","brand":"Prefabricated Aluminum Metal Canopies","generic name":"Matsoft"},
{"sku":700203,"name":"Pterogonium Moss","brand":"HVAC","generic name":"Viva"},
{"sku":536835,"name":"Pale Ditrichum Moss","brand":"Roofing (Metal)","generic name":"Viva"},
{"sku":114491,"name":"Mill Creek Agoseris","brand":"HVAC","generic name":"Asoka"},
{"sku":150859,"name":"Madieravine","brand":"Fire Sprinkler System","generic name":"Bytecard"},
{"sku":973383,"name":"Groundsel","brand":"Marlite Panels (FED)","generic name":"Tempsoft"},
{"sku":71422,"name":"Goodrich Eared Rockcress","brand":"Elevator","generic name":"Cardify"},
{"sku":327773,"name":"Marsh Grass","brand":"Epoxy Flooring","generic name":"Redhold"},
{"sku":325301,"name":"Purple Meadowparsnip","brand":"Elevator","generic name":"Flowdesk"},
{"sku":312297,"name":"Modoc Hawksbeard","brand":"Glass & Glazing","generic name":"Voyatouch"}]